explainable_cnn/__init__.py
explainable_cnn/explainers/__init__.py
explainable_cnn/explainers/base_explainer.py
explainable_cnn/explainers/cnn_explainer.py
explainable_cnn/explainers/grad_cam.py
explainable_cnn/validators/__init__.py
explainable_cnn/validators/base_validator.py
explainable_cnn/validators/cnn_validator.py
explainable_cnn-1.0.0.dist-info/LICENSE
explainable_cnn-1.0.0.dist-info/METADATA
explainable_cnn-1.0.0.dist-info/WHEEL
explainable_cnn-1.0.0.dist-info/top_level.txt
explainable_cnn-1.0.0.dist-info/RECORD
