Metadata-Version: 2.1
Name: explainable-cnn
Version: 1.0.0
Summary: 📦 Flexible visualization package for generatinglayer-wise explanations for CNNs.
Home-page: https://github.com/ashutosh1919/explainable-cnn
Author: Ashutosh Hathidara
Author-email: ashutoshhathidara98@gmail.com
Project-URL: Bug Tracker, https://github.com/ashutosh1919/explainable-cnn/issues
Classifier: Programming Language :: Python :: 3
Classifier: License :: OSI Approved :: MIT License
Classifier: Operating System :: OS Independent
Requires-Python: >=3.6
License-File: LICENSE
